AUTHORS.rst
CONTRIBUTING.rst
HISTORY.rst
LICENSE
MANIFEST.in
README.rst
setup.py
cheddar/__init__.py
cheddar/app.py
cheddar/auth.py
cheddar/configure.py
cheddar/controllers.py
cheddar/defaults.py
cheddar/development.py
cheddar/errorhandlers.py
cheddar/exceptions.py
cheddar/history.py
cheddar/production.py
cheddar.egg-info/PKG-INFO
cheddar.egg-info/SOURCES.txt
cheddar.egg-info/dependency_links.txt
cheddar.egg-info/entry_points.txt
cheddar.egg-info/requires.txt
cheddar.egg-info/top_level.txt
cheddar/index/__init__.py
cheddar/index/combined.py
cheddar/index/index.py
cheddar/index/local.py
cheddar/index/remote.py
cheddar/index/storage.py
cheddar/model/__init__.py
cheddar/model/distribution.py
cheddar/model/versions.py
cheddar/templates/base.html
cheddar/templates/index.html
cheddar/templates/nav.html
cheddar/templates/project.html
cheddar/templates/simple.html
cheddar/templates/version.html
cheddar/tests/index/__init__.py
cheddar/tests/index/test_remote.py
cheddar/tests/model/__init__.py
cheddar/tests/model/test_versions.py