Metadata-Version: 1.0
Name: cheddar
Version: 1.4
Summary: PyPI clone with Flask and Redis
Home-page: https://github.com/jessemyers/cheddar
Author: Jesse Myers
Author-email: jesse@locationlabs.com
License: UNKNOWN
Platform: UNKNOWN
